notion2sql/__init__.py
notion2sql/core/__init__.py
notion2sql/core/client.py
notion2sql/core/database.py
notion2sql/core/page.py
notion2sql/core/sql_interface.py
notion2sql/utils/__init__.py
notion2sql/utils/property_converter.py
notion2sql-0.1.1.dist-info/licenses/LICENSE
tests/__init__.py
tests/test_client.py
notion2sql-0.1.1.dist-info/METADATA
notion2sql-0.1.1.dist-info/WHEEL
notion2sql-0.1.1.dist-info/top_level.txt
notion2sql-0.1.1.dist-info/RECORD
