Metadata-Version: 2.4
Name: notion2sql
Version: 0.1.1
Summary: 一个将Notion数据库转换为SQL接口的工具
Home-page: https://github.com/randallanjie/notion2sql
Author: Randall
Author-email: randall@randallanjie.com
Classifier: Programming Language :: Python :: 3
Classifier: License :: OSI Approved :: MIT License
Classifier: Operating System :: OS Independent
Requires-Python: >=3.7
License-File: LICENSE
Requires-Dist: notion-client>=2.0.0
Requires-Dist: requests>=2.25.1
Requires-Dist: python-dotenv>=0.19.0
Requires-Dist: SQLAlchemy>=1.4.0
Requires-Dist: pytest>=6.2.5
Dynamic: author
Dynamic: author-email
Dynamic: classifier
Dynamic: description
Dynamic: description-content-type
Dynamic: home-page
Dynamic: license-file
Dynamic: requires-dist
Dynamic: requires-python
Dynamic: summary
